{"data":[{"id":24,"created_at":"2023-04-10 15:43:11","updated_at":"2023-04-10 15:43:11","libelle":"KCorp testing","max_teams":16,"enroll":0,"is_highlighted":1,"state":"CLOSE","skill_level":"Débutant","speech":"Venez affronter la nouvelle KCorp","best_of":3,"format":"3 vs 3","begin_at":"2023-04-10 15:43:11","challonge_id":null,"owner":4,"image_bracket":null},{"id":25,"created_at":"2023-04-10 15:43:11","updated_at":"2023-04-10 15:43:11","libelle":"Training to US","max_teams":64,"enroll":0,"is_highlighted":1,"state":"OPEN","skill_level":"Tous","speech":null,"best_of":1,"format":"2 vs 2","begin_at":"2023-04-10 15:43:11","challonge_id":null,"owner":3,"image_bracket":null},{"id":26,"created_at":"2023-04-10 15:43:11","updated_at":"2023-04-10 15:43:11","libelle":"Vendredi 20h","max_teams":32,"enroll":0,"is_highlighted":0,"state":"OPEN","skill_level":"Tous","speech":null,"best_of":3,"format":"1 vs 1","begin_at":"2023-04-10 15:43:11","challonge_id":null,"owner":2,"image_bracket":null},{"id":27,"created_at":"2023-04-10 15:43:11","updated_at":"2023-04-10 15:43:11","libelle":"Lundi 22h","max_teams":16,"enroll":0,"is_highlighted":0,"state":"OPEN","skill_level":"Tous","speech":null,"best_of":2,"format":"2 vs 2","begin_at":"2023-04-10 15:43:11","challonge_id":null,"owner":1,"image_bracket":null},{"id":28,"created_at":"2023-04-10 15:43:11","updated_at":"2023-04-10 15:43:11","libelle":"Mardi 20h","max_teams":8,"enroll":0,"is_highlighted":0,"state":"OPEN","skill_level":"Pro","speech":"Go go go","best_of":5,"format":"2 vs 2","begin_at":"2023-04-10 15:43:11","challonge_id":null,"owner":2,"image_bracket":null}],"total":32}